syncio/Multiprocessing.py
syncio/Task.py
syncio/Threading.py
syncio/__init__.py
syncio/py.typed
syncio-0.0.4.dist-info/METADATA
syncio-0.0.4.dist-info/WHEEL
syncio-0.0.4.dist-info/top_level.txt
syncio-0.0.4.dist-info/RECORD
