Metadata-Version: 2.1
Name: syncio
Version: 0.0.4
Summary: type safety for synchronous concurrent task
Home-page: https://github.com/guangrei/syncio
Author: guangrei
Author-email: myawn@pm.me
License: MIT
Platform: any
Requires-Dist: typing-extensions
